ganzoo/__init__.py
ganzoo/__version__.py
ganzoo/constants/__init__.py
ganzoo/constants/data_constants.py
ganzoo/constants/defaults.py
ganzoo/constants/names.py
ganzoo/lit_modules/__init__.py
ganzoo/lit_modules/basic_fc_gan.py
ganzoo/lit_modules/dcgan.py
ganzoo/lit_modules/lit_data_custom.py
ganzoo/lit_modules/lit_data_vision.py
ganzoo/losses/__init__.py
ganzoo/losses/basic_losses.py
ganzoo/losses/wgan_losses.py
ganzoo/misc/__init__.py
ganzoo/misc/ops.py
ganzoo/misc/torch_ops.py
ganzoo/misc/utils.py
ganzoo/nn_modules/__init__.py
ganzoo/nn_modules/dcgan_nets.py
ganzoo/nn_modules/fc_nets.py
run/basic_gan/__init__.py
run/basic_gan/eval_dcgan.py
run/basic_gan/eval_fc.py
run/basic_gan/parser_dcgan.py
run/basic_gan/parser_fc.py
run/basic_gan/train_dcgan.py
run/basic_gan/train_fc.py
pytorch_gan_zoo-0.0.6.dist-info/METADATA
pytorch_gan_zoo-0.0.6.dist-info/WHEEL
pytorch_gan_zoo-0.0.6.dist-info/top_level.txt
pytorch_gan_zoo-0.0.6.dist-info/RECORD
