Metadata-Version: 2.1
Name: pytorch-gan-zoo
Version: 0.0.6
Summary: Implementation of GAN models in PyTorch.
Home-page: https://github.com/vmirly/pytorch-gan-zoo
Maintainer: Vahid Mirjalili
Requires-Python: >=3.6.0
